{
  "categorias": [
    {
      "titulo": "Finances",
      "link": "https://www.youtube.com/watch?v=QnJ70T438qU",
      "cor": "#6BD1FF",
      "link_extra": {
        "text": "Canais de finanças para dominarmos o nosso suado dinheirinho",
        "url": "https://www.youtube.com/results?search_query=finan%C3%A7as&page=&utm_source=opensearch"
      },
      "videos": [
        {
          "titulo": "COMO AUMENTAR O SCORE: Guia INFALÍVEL",
          "url": "https://www.youtube.com/watch?v=J-iJsYEhA8M"
        },
        {
          "titulo": "MEU PRIMEIRO MILHÃO: Como fiquei milionária com 32 anos",
          "url": "https://www.youtube.com/watch?v=4jaWDfTbytA"
        },
        {
          "titulo": "Como administrar as finanças de sua empresa? - #CerbasiResponde",
          "url": "https://www.youtube.com/watch?v=MtFxmFYioas"
        },
        {
          "titulo": "POR QUE EU ACORDO ÀS 4:30 DA MANHÃ? | 5AM Club (o clube das 5)",
          "url": "https://www.youtube.com/watch?v=CGI2LJAcz0A"
        },
        {
          "titulo": "EDUCAÇÃO É UM GASTO OU UM INVESTIMENTO? | NATH FINANÇAS",
          "url": "https://www.youtube.com/watch?v=4i50eZ_DPvw"
        }       
      ]
    },
    {
      "titulo": "Business",
      "cor": "#00C86F",
      "link_extra": {
        "text": "Estude sobre negócios e colabore no desenvolvimento de nossa Nação, através do Empreendedorismo!",
        "url": "https://www.sebrae.com.br"
      },
      "videos": [
        {
          "titulo": "7 IDEIAS DE NEGÓCIOS (PEQUENOS) para AUMENTAR a sua RENDA",
          "url": "https://www.youtube.com/watch?v=H3DePqT2ad8"
        },
        {
          "titulo": "5 NEGÓCIOS nos EUA que ainda NÃO chegaram no BRASIL! (Negócios rentáveis do futuro)",
          "url": "https://www.youtube.com/watch?v=25w_d0d96Qc"
        },
        {
          "titulo": "A INCRÍVEL VIDA DE WARREN BUFFETT | Histórias de Sucesso #01",
          "url": "https://www.youtube.com/watch?v=2aDySEqiy0o"
        },
        {
          "titulo": "O FUTURO DOS NEGÓCIOS DEPOIS DO CORONAVÍRUS: QUEM VAI LUCRAR OU QUEBRAR?",
          "url": "https://www.youtube.com/watch?v=a2kzPlKTKLk"
        }
      ]
    },
    {
      "titulo": "Gaming",
      "cor": "#9cd33b",
      "link_extra": {
        "text": "Participe da comunidade CODM no Brasil!",
        "url": "https://www.callofduty.com/br/pt/mobile"
      },
      "videos": [
        {
          "titulo": "NOVO BATTLE ROYALE SEASON 9 NO CALL OF DUTY MOBILE VIROU WARZONE - MUDANCAS E NOVIDADES",
          "url": "https://www.youtube.com/watch?v=Kmen9ME2Lps"
        },
        {
          "titulo": "🏆GRAND FINALS | Philippines National Championship | Call of Duty®:Mobile -Garena",
          "url": "https://www.youtube.com/watch?v=WkMV5kmzmes"
        },
        {
          "titulo": "COD Mobile - ARMA **LENDÁRIA de LAVA** | Sorteio Ponto de Fusão QQ9 E Mace na Season 8",
          "url": "https://www.youtube.com/watch?v=BZmb9OhpouA"
        }
      ]
    },
    {
      "titulo": "Music & Dancing",
      "cor": "orange",
      "videos": [
        {
          "titulo": "Lil Nas X - Old Town Road (Official Movie) ft. Billy Ray Cyrus",
          "url": "https://www.youtube.com/watch?v=w2Ov5jzm3j8"
        },
        {
          "titulo": "Can't Help Falling In Love - Elvis Cover by 6-Year-Old Claire Crosby",
          "url": "https://www.youtube.com/watch?v=VlPdfLr1FSo"
        },
        {
          "titulo": "Tico Tico no Fubá - Duo Siqueira Lima - 4 Hands",
          "url": "https://www.youtube.com/watch?v=NVitgDEh_tw"
        },
        {
          "titulo": "KRYPTO9095 FT. D3MSTREET WOAH (OFFICIAL SONG TO WOAH DANCE)",
          "url": "https://www.youtube.com/watch?v=afRki2_aNKg"
        }
      ]
    },
    {
      "titulo": "Other stuff",
      "cor": "red",
      "link_extra": {
        "text": "Espaço do aleatório",
        "url": "/"
      },
      "videos": [
        {
          "titulo": "COMO JOGAR MINECRAFT NA BANANA !",
          "url": "https://www.youtube.com/watch?v=SMvh0Vkt-50"
        },
        {
          "titulo": "Nota de R$ 200: por que agora e qual a razão de tanta polêmica?",
          "url": "https://www.youtube.com/watch?v=u0A5Opejy2k"
        },
        {
          "titulo": "Tirulive / Tirullipa Show / O rei das lives",
          "url": "https://www.youtube.com/watch?v=O-jSTC3L-TA"
        },
        {
          "titulo": "Entrevista com Cabo Daciolo | The Noite (29/07/20)",
          "url": "https://www.youtube.com/watch?v=JX-ahxIfwSE"
        }
      ]
    },
    {
      "titulo": "Aprendendo a aprender tecnologia",
      "cor": "#6b5be2",
      "link_extra": {
        "text": "Curso sobre aprendizado na Alura",
        "url": "https://alura.com.br/curso-online-aprender-a-aprender-tecnicas-para-seu-autodesenvolvimento"
      },
      "videos": [
        {
          "titulo": "Como estudar melhor?",
          "url": "https://www.youtube.com/watch?v=Is6c9KSGCbk&feature=youtu.be"
        },
        {
          "titulo": "Faculdade",
          "url": "https://www.youtube.com/watch?v=jw06H8esyzQ&feature=youtu.be"
        },
        {
          "titulo": "Frameworks",
          "url": "https://www.youtube.com/watch?v=QzDjdlF1BQI"
        },
        {
          "titulo": "A mágica do Aprendizado",
          "url": "https://www.youtube.com/watch?v=oTEXzpfEpPY"
        },
        {
          "titulo": "Como aprender a programar?",
          "url": "https://www.youtube.com/watch?v=MwCx2qKdbDw&feature=youtu.be"
        }
      ]
    }
  ]
}